amqp_mqtt_transport/__init__.py
amqp_mqtt_transport/abc.py
amqp_mqtt_transport/message_scheduler.py
amqp_mqtt_transport/scheduled_publisher.py
amqp_mqtt_transport/amqp/__init__.py
amqp_mqtt_transport/amqp/consumer.py
amqp_mqtt_transport/amqp/controller.py
amqp_mqtt_transport/amqp/publisher.py
amqp_mqtt_transport/amqp/workers.py
amqp_mqtt_transport/mqtt/__init__.py
amqp_mqtt_transport/mqtt/controller.py
amqp_mqtt_transport/mqtt/publisher.py
amqp_mqtt_transport-0.1.22.dist-info/LICENSE
amqp_mqtt_transport-0.1.22.dist-info/METADATA
amqp_mqtt_transport-0.1.22.dist-info/WHEEL
amqp_mqtt_transport-0.1.22.dist-info/top_level.txt
amqp_mqtt_transport-0.1.22.dist-info/RECORD
